api_secrets.py
api_secrets-1.23.dist-info/METADATA
api_secrets-1.23.dist-info/WHEEL
api_secrets-1.23.dist-info/licenses/LICENSE
api_secrets-1.23.dist-info/RECORD
