Metadata-Version: 2.1
Name: api_secrets
Version: 1.23
Summary: A wrapper package to manage specific cross-platform management requirements including supplementary data (i.e. URLs)
Author-email: Brodie Zambergs <brodie.zambergs@monash.edu>
License-File: LICENSE
Classifier: License :: OSI Approved :: MIT License
Classifier: Operating System :: OS Independent
Classifier: Programming Language :: Python :: 3
Requires-Python: >=3.7
